rlupat_toyrobot-0.2.3.dist-info/licenses/LICENSE
toyrobot/__init__.py
toyrobot/app.py
toyrobot/models/__init__.py
toyrobot/models/orientation.py
toyrobot/models/robot.py
toyrobot/models/tabletop.py
toyrobot/parser/__init__.py
toyrobot/parser/commandparser.py
toyrobot/test/__init__.py
toyrobot/test/test_commandparser.py
toyrobot/test/test_main.py
toyrobot/test/test_orientation.py
toyrobot/test/test_robot.py
toyrobot/test/test_tabletop.py
rlupat_toyrobot-0.2.3.dist-info/METADATA
rlupat_toyrobot-0.2.3.dist-info/WHEEL
rlupat_toyrobot-0.2.3.dist-info/entry_points.txt
rlupat_toyrobot-0.2.3.dist-info/top_level.txt
rlupat_toyrobot-0.2.3.dist-info/RECORD
