Metadata-Version: 2.4
Name: rlupat.toyrobot
Version: 0.2.3
Summary: ToyRobot Example Implementation
Author: Richard Lupat
License: MIT
License-File: LICENSE
Requires-Dist: wheel
Requires-Dist: setuptools
Requires-Dist: twine
Dynamic: author
Dynamic: description
Dynamic: description-content-type
Dynamic: license
Dynamic: license-file
Dynamic: requires-dist
Dynamic: summary
